glorpen_di-1.5.0-py3.6-nspkg.pth
glorpen/di/__init__.py
glorpen/di/container.py
glorpen/di/exceptions.py
glorpen/di/scopes.py
glorpen_di-1.5.0.dist-info/METADATA
glorpen_di-1.5.0.dist-info/WHEEL
glorpen_di-1.5.0.dist-info/namespace_packages.txt
glorpen_di-1.5.0.dist-info/top_level.txt
glorpen_di-1.5.0.dist-info/RECORD
