Metadata-Version: 2.1
Name: glorpen-di
Version: 1.5.0
Summary: Yet another Dependency Injection (IOC) component for Python
Home-page: https://bitbucket.org/glorpen/glorpen-di
Author: Arkadiusz Dzięgiel
Author-email: arkadiusz.dziegiel@glorpen.pl
License: GPLv3
Platform: UNKNOWN
Classifier: Development Status :: 5 - Production/Stable
Classifier: Intended Audience :: Developers
Classifier: License :: OSI Approved :: GNU General Public License v3 or later (GPLv3+)
Classifier: Programming Language :: Python
Classifier: Programming Language :: Python :: 2.7
Classifier: Programming Language :: Python :: 3
Classifier: Programming Language :: Python :: 3.2
Classifier: Programming Language :: Python :: 3.3
Classifier: Programming Language :: Python :: 3.4
Classifier: Programming Language :: Python :: 3.5
Classifier: Programming Language :: Python :: 3.6
Classifier: Topic :: Software Development :: Libraries
Requires-Dist: six (>=1.9)
